happy_face/__init__.py
happy_face/happy_face.py
happy_face-0.0.1.dist-info/LICENSE
happy_face-0.0.1.dist-info/METADATA
happy_face-0.0.1.dist-info/WHEEL
happy_face-0.0.1.dist-info/top_level.txt
happy_face-0.0.1.dist-info/RECORD
