Metadata-Version: 2.1
Name: happy-face
Version: 0.0.1
Summary: Recognize and detect faces in an extremely easy way
Home-page: https://github.com/rodrigoherrerai/happy_face
Author: Rodrigo Herrera Itie
Author-email: rheitie@gmail.com
License: UNKNOWN
Platform: UNKNOWN
Classifier: Programming Language :: Python :: 3
Classifier: License :: OSI Approved :: MIT License
Classifier: Operating System :: OS Independent
Requires-Python: >=3.7
License-File: LICENSE
